[
  {
    "id": "SAT-001",
    "ticket_id": "TKT-001",
    "agent_id": "AGT-006",
    "rating": 5,
    "comment": "Aisha tracked down the root cause quickly and kept us updated throughout. VPN has been solid since the fix.",
    "submitted_at": "2025-11-05T09:00:00Z"
  },
  {
    "id": "SAT-002",
    "ticket_id": "TKT-002",
    "agent_id": "AGT-001",
    "rating": 4,
    "comment": "Calendar sync fixed. Took a bit longer than expected but Marcus was helpful.",
    "submitted_at": "2025-11-08T10:00:00Z"
  },
  {
    "id": "SAT-003",
    "ticket_id": "TKT-003",
    "agent_id": "AGT-003",
    "rating": 4,
    "comment": "James got me a replacement keyboard within a few days. Smooth process.",
    "submitted_at": "2025-11-16T08:00:00Z"
  },
  {
    "id": "SAT-004",
    "ticket_id": "TKT-005",
    "agent_id": "AGT-004",
    "rating": 5,
    "comment": "Network was back up in under 4 hours during a critical outage. Great response from Elena and the team.",
    "submitted_at": "2025-11-21T09:00:00Z"
  },
  {
    "id": "SAT-005",
    "ticket_id": "TKT-007",
    "agent_id": "AGT-005",
    "rating": 4,
    "comment": "David figured out it was a corrupted cache directory. Quick fix once identified.",
    "submitted_at": "2025-12-03T08:00:00Z"
  },
  {
    "id": "SAT-006",
    "ticket_id": "TKT-008",
    "agent_id": "AGT-006",
    "rating": 5,
    "comment": "Shared mailbox was created with all permissions set up correctly on the first try.",
    "submitted_at": "2025-12-05T16:00:00Z"
  },
  {
    "id": "SAT-007",
    "ticket_id": "TKT-009",
    "agent_id": "AGT-002",
    "rating": 3,
    "comment": "Account was eventually unlocked but it took until Monday morning. Would have been better to have it ready Friday evening.",
    "submitted_at": "2025-12-08T11:00:00Z"
  },
  {
    "id": "SAT-008",
    "ticket_id": "TKT-011",
    "agent_id": "AGT-007",
    "rating": 5,
    "comment": "Robert identified the memory leak source and patched it. Jenkins has been stable since. Excellent root cause analysis.",
    "submitted_at": "2025-12-12T10:00:00Z"
  },
  {
    "id": "SAT-009",
    "ticket_id": "TKT-014",
    "agent_id": "AGT-001",
    "rating": 3,
    "comment": "Printer is working now but took a while to get someone out to look at it. Had to use a different floor in the meantime.",
    "submitted_at": "2025-12-21T14:00:00Z"
  },
  {
    "id": "SAT-010",
    "ticket_id": "TKT-015",
    "agent_id": "AGT-006",
    "rating": 4,
    "comment": "Forwarding rule was fixed. Turned out Exchange Online had changed the connector settings during an update.",
    "submitted_at": "2025-12-25T16:00:00Z"
  },
  {
    "id": "SAT-011",
    "ticket_id": "TKT-017",
    "agent_id": "AGT-003",
    "rating": 5,
    "comment": "James got the battery replaced same day. Laptop runs great now.",
    "submitted_at": "2026-01-09T14:00:00Z"
  },
  {
    "id": "SAT-012",
    "ticket_id": "TKT-018",
    "agent_id": "AGT-007",
    "rating": 4,
    "comment": "Equipment arrived quickly. The ergonomic keyboard has helped a lot with the wrist pain.",
    "submitted_at": "2026-01-13T10:00:00Z"
  },
  {
    "id": "SAT-013",
    "ticket_id": "TKT-020",
    "agent_id": "AGT-005",
    "rating": 2,
    "comment": "The suggested fix of increasing memory allocation helped temporarily but the indexing issue came back after a few days. Had to follow up again.",
    "submitted_at": "2026-01-21T11:00:00Z"
  },
  {
    "id": "SAT-014",
    "ticket_id": "TKT-021",
    "agent_id": "AGT-007",
    "rating": 5,
    "comment": "Robert ran a great orientation session. New hires all had their accounts and tools ready on day one.",
    "submitted_at": "2026-02-05T09:00:00Z"
  },
  {
    "id": "SAT-015",
    "ticket_id": "TKT-028",
    "agent_id": "AGT-007",
    "rating": 4,
    "comment": "Split-tunnel policy was updated and tested. Bandwidth issues resolved for the contractor team.",
    "submitted_at": "2026-02-22T10:00:00Z"
  }
]
